LICENSE
MANIFEST.in
README.md
appearance.py
packages.py
setup.py
updates.py
docs/index.rst
updates.egg-info/PKG-INFO
updates.egg-info/SOURCES.txt
updates.egg-info/dependency_links.txt
updates.egg-info/entry_points.txt
updates.egg-info/top_level.txt